{
  "tantos | tantas":"so many",
  "maravilloso | maravillosa | maravillosas":"wonderful",
  "árbol | árboles":"tree | trees",
  "a lo largo de":"along | throughout",
  "rompecabezas":"puzzle | puzzles",
  "la postal":"the postcard",
  "coleccionar | colecciono | coleccionas | colecciona | coleccionamos | coleccionan":"collecting | collect | to collect | ...",
  "esquiar | esquío | esquías | esquía | esquiamos | esquían":"ski | to ski | skiing | ...",
  "navegar | navego | navegas | navega | navegamos | navegan":"sail | sailing | surf | ...",
  "velero":"sailboat",
  "prestar | presto | prestas | presta | prestamos | prestan":"lend | to lend | to borrow | ...",
  "haber | he | has | ha, hay | hemos | han":"to have | to be | there is going to be | ...",
  "antes | antes de":"before",
  "bastante":"quite | quite a lot | enough",
  "los obreros | orbrera":"the workers | the working-class",
  "todavía":"yet | still | even",
  "robar | robo | robas | roba | robamos | roban":"steal | to steal | ...",
  "peligro":"danger",
  "la policía":"the police | police officer",
  "salvaje | salvajes":"wild | animals | brutal",
  "el fuego":"the fire",
  "la electricidad":"the electricity",
  "nacional | nacionales":"national",
  "extraño":"strange",
  "robado":"stolen",
  "terrible":"terrible | horrible"
}
